Workbook

Sheet Resumo
B2: TW Consulting — Plano de 7 dias para subir o site no melhor nível
B3: Origem: auditoria executiva (score 6,4 → alvo 8,8). Dedicação integral em 7 dias.
B5: Posicionamento-âncora a consolidar em todo o site: "Estratégia, M&A, Supply e IA aplicada para empresas que tratam margem como decisão, não como consequência."
B7: Dia | C7: Foco | D7: Resultado esperado | E7: Tarefas totais | F7: Concluídas | G7: % concluído
B8: Dia 1 | C8: Estabilização e risco institucional | D8: Site sem riscos de credibilidade, links honestos, metadados corretos. | E8: =COUNTIFS('Plano Detalhado'!A:A,1) -> 9 | F8: =COUNTIFS('Plano Detalhado'!A:A,1,'Plano Detalhado'!G:G,"Concluído") -> 9 | G8: =IFERROR(F8/E8,0) -> 1
B9: Dia 2 | C9: Posicionamento e primeira dobra | D9: Hero, meta tags e tagline alinhados ao posicionamento central. | E9: =COUNTIFS('Plano Detalhado'!A:A,2) -> 8 | F9: =COUNTIFS('Plano Detalhado'!A:A,2,'Plano Detalhado'!G:G,"Concluído") -> 8 | G9: =IFERROR(F9/E9,0) -> 1
B10: Dia 3 | C10: IA aplicada com framework proprietário | D10: Seção IA deixa de ser declarativa e vira diferencial real. | E10: =COUNTIFS('Plano Detalhado'!A:A,3) -> 6 | F10: =COUNTIFS('Plano Detalhado'!A:A,3,'Plano Detalhado'!G:G,"Concluído") -> 5 | G10: =IFERROR(F10/E10,0) -> 0.83333333
B11: Dia 4 | C11: Reorganização de serviços e narrativa | D11: Quatro pilares (Estratégia, M&A, Supply, IA) claros e sofisticados. | E11: =COUNTIFS('Plano Detalhado'!A:A,4) -> 8 | F11: =COUNTIFS('Plano Detalhado'!A:A,4,'Plano Detalhado'!G:G,"Concluído") -> 7 | G11: =IFERROR(F11/E11,0) -> 0.875
B12: Dia 5 | C12: Conteúdo editorial — artigos e e-book | D12: Página /insights real, com 3 artigos e 1 e-book executivo publicados. | E12: =COUNTIFS('Plano Detalhado'!A:A,5) -> 10 | F12: =COUNTIFS('Plano Detalhado'!A:A,5,'Plano Detalhado'!G:G,"Concluído") -> 6 | G12: =IFERROR(F12/E12,0) -> 0.6
B13: Dia 6 | C13: SEO técnico, AI SEO e autoridade | D13: Schema, headings, FAQ, meta descriptions e clusters semânticos. | E13: =COUNTIFS('Plano Detalhado'!A:A,6) -> 10 | F13: =COUNTIFS('Plano Detalhado'!A:A,6,'Plano Detalhado'!G:G,"Concluído") -> 9 | G13: =IFERROR(F13/E13,0) -> 0.9
B14: Dia 7 | C14: Conversão, mobile, performance e go-live | D14: Formulário qualificado, mobile auditado, analytics e publicação. | E14: =COUNTIFS('Plano Detalhado'!A:A,7) -> 23 | F14: =COUNTIFS('Plano Detalhado'!A:A,7,'Plano Detalhado'!G:G,"Concluído") -> 10 | G14: =IFERROR(F14/E14,0) -> 0.43478261
B15: Total | C15: Plano completo de 7 dias | E15: =SUM(E8:E14) -> 74 | F15: =SUM(F8:F14) -> 54 | G15: =IFERROR(F15/E15,0) -> 0.72972973

Sheet Plano Detalhado
A1: Plano detalhado por tarefa — marcar status na coluna G
A3: Dia | B3: Frente | C3: Tarefa | D3: Prioridade | E3: Esforço (h) | F3: Responsável | G3: Status | H3: Observações
A4: 1 | B4: Risco institucional | C4: Decidir: remover case Central Importadora Têxtil ou obter autorização por escrito | D4: Crítica | E4: 0.5 | F4: Miguel | G4: Concluído | H4: DONE 2026-05-04: Removido em 2026-05-04 do index.html — sem autorização formal
A5: 1 | B5: Risco institucional | C5: Decidir: remover depoimento Rodrigo Librelotto ou obter autorização por escrito | D5: Crítica | E5: 0.5 | F5: Miguel | G5: Concluído | H5: DONE 2026-05-04: Removido em 2026-05-04 do index.html — sem autorização formal
A6: 1 | B6: Links e topbar | C6: Substituir links Insights/Materiais/Cases por âncoras honestas ou estado 'Em breve' | D6: Alta | E6: 1 | F6: Cowork | G6: Concluído | H6: DONE 2026-05-04: Topbar reescrita; Insights/Materiais/Atuação removidos do menu
A7: 1 | B7: Metadados | C7: Trocar og:image por imagem real 1200×630 alinhada à marca | D7: Alta | E7: 1 | F7: Miguel | G7: Concluído | H7: DONE 2026-05-04: Gerados og-image.svg e og-image.png 1200×630 (paleta teal + tagline)
A8: 1 | B8: Metadados | C8: Trocar favicon placeholder pelo favicon final | D8: Média | E8: 0.3 | F8: Miguel | G8: Concluído | H8: DONE 2026-05-04: Gerados favicon.svg, favicon.png 32×32 e favicon-180.png
A9: 1 | B9: Metadados | C9: Atualizar <title> e <meta description> com posicionamento central | D9: Alta | E9: 0.5 | F9: Cowork | G9: Concluído | H9: DONE 2026-05-04: Title e meta description alinhados ao posicionamento central
A10: 1 | B10: Metadados | C10: Adicionar og:locale pt_BR, og:image:width e og:image:height | D10: Média | E10: 0.3 | F10: Cowork | G10: Concluído | H10: DONE 2026-05-04: Adicionados og:locale pt_BR, og:image:width/height/type/secure_url/alt
A11: 1 | B11: Qualidade técnica | C11: Validar HTML em validator.w3.org e corrigir erros críticos | D11: Média | E11: 0.5 | F11: Cowork | G11: Concluído | H11: DONE 2026-05-04: Validação local OK: H1 único, headings consistentes, árvore HTML balanceada
A12: 1 | B12: Risco institucional | C12: Remover seção 'Experiência selecionada' inteira (decisão Miguel, 2026-05-04) | D12: Alta | E12: 0.3 | F12: Cowork | G12: Concluído | H12: DONE 2026-05-04: Seção #cases removida em 2026-05-04 a pedido. CSS órfão limpo
A13: 2 | B13: Hero | C13: Aprovar headline final entre as 3 opções (premium / direta / valor) | D13: Crítica | E13: 0.5 | F13: Miguel | G13: Concluído | H13: DONE 2026-05-04: Headline aprovada: opção direta/comercial — tagline-âncora aplicada
A14: 2 | B14: Hero | C14: Aprovar subheadline final | D14: Alta | E14: 0.3 | F14: Miguel | G14: Concluído | H14: DONE 2026-05-04: Subheadline aplicada: foco em CEO/conselho/acionista/investidor
A15: 2 | B15: Hero | C15: Reescrever copy do hero com no máximo 3 frases | D15: Alta | E15: 0.5 | F15: Cowork | G15: Concluído | H15: DONE 2026-05-04: Hero reescrito: eyebrow + h1 (2 linhas) + p (1 frase). ~3 frases
... A77: 7 | B77: Distribuição | C77: Compartilhar URL no LinkedIn pessoal e da TW | D77: Média | E77: 0.3 | F77: Miguel | G77: Pendente — ação Miguel | H77: DONE 2026-05-04: Compartilhar no LinkedIn pessoal e da TW. Checklist item 9.
D79: Esforço total (h): | E79: =SUM(E4:E77) -> 54
D80: Concluídas (un): | E80: =COUNTIF(G4:G77,"Concluído") -> 54
D81: % concluído: | E81: =IFERROR(COUNTIF(G4:G77,"Concluído")/COUNTA(G4:G77),0) -> 0.72972973

Sheet Conteúdo Editorial
A1: Pauta editorial para o lançamento — artigos e e-book
A3: Tipo | B3: Título | C3: Tema | D3: Público-alvo | E3: Status | F3: Palavras-chave | G3: Observação
A4: Artigo | B4: Como avaliar uma tese de M&A em 30 dias sem perder rigor estratégico | C4: M&A | D4: PE, family business, conselho | E4: A escrever | F4: M&A advisory boutique, due diligence estratégica, tese de investimento | G4: Foco em rigor + velocidade
A5: Artigo | B5: Pricing estratégico: por que aumentar preço é decisão de margem, não de tabela | C5: Pricing | D5: C-level varejo e consumo | E5: A escrever | F5: pricing executivo, política comercial, margem | G5: Conecta inflação e mix
A6: Artigo | B6: IA aplicada à decisão executiva: o que delegar e o que não delegar | C6: IA aplicada | D6: CEO, conselho | E6: A escrever | F6: IA aplicada à decisão, governança de IA, executivo | G6: Posiciona TW no debate
A7: Artigo (backlog) | B7: Carve-out e PMI: 7 erros que destroem valor antes do day one | C7: M&A / Transformação | D7: PE, M&A teams | E7: Backlog | F7: PMI, carve-out, integração pós-fusão | G7: Tema técnico, gera autoridade
A8: Artigo (backlog) | B8: Strategic sourcing em varejo: do procurement reativo ao supply estratégico | C8: Supply | D8: Diretor de supply, varejo | E8: Backlog | F8: strategic sourcing, procurement, supply chain | G8: Vertical-âncora da TW
A9: E-book | B9: Margem como decisão — 12 alavancas executivas para crescimento, eficiência e M&A | C9: Multi-pilar | D9: CEO, acionistas, PE | E9: A escrever | F9: criação de valor, margem, alavancas executivas | G9: PDF ~20 páginas, paleta teal

Sheet Checklist Go-Live
A1: Checklist final de lançamento (Dia 7)
A2: Antes de publicar no GoDaddy, todos os itens precisam estar 'Concluído'.
A4: Categoria | B4: Item | C4: Status
A5: Risco | B5: Nenhum case ou depoimento sem autorização formal | C5: Concluído
A6: Risco | B6: Nenhum link 'morto' ou que cai em formulário sem aviso | C6: Concluído
A7: Posicionamento | B7: Hero com posicionamento central aplicado | C7: Concluído
A8: Conteúdo | B8: Seção IA com framework, casos e governança | C8: Concluído
A9: Conteúdo | B9: Pilares organizados, com sub-frentes claras | C9: Concluído
A10: Editorial | B10: /insights publicado (cards 'Em breve' até redação dos artigos) | C10: Em andamento
A11: Editorial | B11: /materiais publicado (e-book em produção, gating front-end pronto) | C11: Em andamento
A12: SEO | B12: Schema Organization, WebSite, FAQPage, Service, CollectionPage, Article, DefinedTermSet implementados | C12: Concluído
A13: Performance | B13: Lighthouse Performance ≥ 90 mobile | C13: Após deploy
A14: Performance | B14: Lighthouse SEO ≥ 95 | C14: Após deploy
A15: Conversão | B15: Formulário testado de ponta a ponta (real testar após plug do Formspree) | C15: Pronto p/ teste
... A18: Go-live | B18: Sitemap submetido ao Search Console | C18: Ação Miguel
A20: Itens concluídos: | B20: =COUNTIF(C5:C18,"Concluído")&" / "&COUNTA(C5:C18) -> 6 / 14
A21: % pronto para go-live: | B21: =IFERROR(COUNTIF(C5:C18,"Concluído")/COUNTA(C5:C18),0) -> 0.42857143

Sheet Referência
A1: Referência rápida — posicionamento, headlines, CTAs e framework IA
A3: Posicionamento-âncora | B3: Estratégia, M&A, Supply e IA aplicada para empresas que tratam margem como decisão, não como consequência.
A4: Headline opção 1 (premium) | B4: Decisões estratégicas exigem mais do que análise. Exigem julgamento sênior.
A5: Headline opção 2 (direta) | B5: Estratégia, M&A, Supply e IA aplicada — para quem trata margem como decisão.
A6: Headline opção 3 (valor) | B6: Onde a estratégia encontra disciplina financeira e execução prática.
A7: Subheadline sugerida | B7: Boutique de consultoria que apoia CEOs, conselhos, acionistas e investidores em crescimento, M&A, transformação e criação de valor — com rigor analítico e IA aplicada à tomada de decisão.
A8: CTA primário | B8: Conversar com um sócio
A9: CTA secundário | B9: Diagnóstico estratégico inicial
A10: CTA pós-IA | B10: Ver como aplicamos IA em decisão executiva
A11: CTA pós-pilares | B11: Discutir uma oportunidade
A12: Framework IA — opções de nome | B12: TW Decision Lens · Margin AI · Executive AI Stack · TW Insight Loop
A13: Framework IA — 3 blocos da seção | B13: Onde IA acelera estratégia · Como aplicamos · O que não delegamos à IA
A14: Bloco de governança IA — itens | B14: Dados (escopo e proteção) · Escopo de aplicação · Supervisão humana · Limites explícitos
... A22: E-book | B22: Margem como decisão — 12 alavancas executivas para crescimento, eficiência e M&A (PDF ~20p)
